pystack_cli/__init__.py
pystack_cli-1.0.2.data/scripts/pystack
pystack_cli-1.0.2.data/scripts/pystack.bat
pystack_cli-1.0.2.dist-info/LICENSE
pystack_cli-1.0.2.dist-info/METADATA
pystack_cli-1.0.2.dist-info/WHEEL
pystack_cli-1.0.2.dist-info/top_level.txt
pystack_cli-1.0.2.dist-info/RECORD
