Metadata-Version: 2.1
Name: pystack-cli
Version: 1.0.2
Summary: PyStack micro-framework command line interface
Home-page: https://github.com/zoltancsontos/pystack.sh-cli
Author: Zoltan Csontos
Author-email: zoltan.csontos.dev@gmail.com
License: UNKNOWN
Platform: UNKNOWN
Classifier: Programming Language :: Python :: 3
Classifier: License :: OSI Approved :: MIT License
Classifier: Operating System :: OS Independent
